odoo/addons/purchase_v12_control_menu/README.rst
odoo/addons/purchase_v12_control_menu/__init__.py
odoo/addons/purchase_v12_control_menu/__manifest__.py
odoo/addons/purchase_v12_control_menu/i18n/es.po
odoo/addons/purchase_v12_control_menu/i18n/it.po
odoo/addons/purchase_v12_control_menu/i18n/purchase_v12_control_menu.pot
odoo/addons/purchase_v12_control_menu/readme/CONTRIBUTORS.md
odoo/addons/purchase_v12_control_menu/readme/DESCRIPTION.md
odoo/addons/purchase_v12_control_menu/static/description/icon.png
odoo/addons/purchase_v12_control_menu/static/description/index.html
odoo/addons/purchase_v12_control_menu/views/purchase_views.xml
odoo_addon_purchase_v12_control_menu-17.0.1.0.0.3.dist-info/METADATA
odoo_addon_purchase_v12_control_menu-17.0.1.0.0.3.dist-info/WHEEL
odoo_addon_purchase_v12_control_menu-17.0.1.0.0.3.dist-info/top_level.txt
odoo_addon_purchase_v12_control_menu-17.0.1.0.0.3.dist-info/RECORD
