Metadata-Version: 2.1
Name: odoo-addon-purchase_v12_control_menu
Version: 17.0.1.0.0.3
Requires-Python: >=3.10
Requires-Dist: odoo>=17.0a,<17.1dev
Summary: Purchase Control Menu from v12
Home-page: https://github.com/OCA/purchase-workflow
License: LGPL-3
Author: Tecnativa, Odoo S.A., Odoo Community Association (OCA)
Author-email: support@odoo-community.org
Classifier: Programming Language :: Python
Classifier: Framework :: Odoo
Classifier: Framework :: Odoo :: 17.0
Classifier: License :: OSI Approved :: GNU Lesser General Public License v3 (LGPLv3)
